ploomber_extension/__init__.py
ploomber_extension/_version.py
ploomber_extension/server_handlers/dashboard.py
ploomber_extension-0.1.1.data/data/etc/jupyter/jupyter_server_config.d/ploomber_extension.json
ploomber_extension-0.1.1.data/data/share/jupyter/labextensions/ploomber-extension/package.json
ploomber_extension-0.1.1.data/data/share/jupyter/labextensions/ploomber-extension/schemas/ploomber-extension/package.json.orig
ploomber_extension-0.1.1.data/data/share/jupyter/labextensions/ploomber-extension/schemas/ploomber-extension/settings.json
ploomber_extension-0.1.1.data/data/share/jupyter/labextensions/ploomber-extension/static/104.3fd2d5b9f5d9e01d67f3.js
ploomber_extension-0.1.1.data/data/share/jupyter/labextensions/ploomber-extension/static/132.a11bf2d79b83c55b689a.js
ploomber_extension-0.1.1.data/data/share/jupyter/labextensions/ploomber-extension/static/156.491a93129c84d26e6681.js
ploomber_extension-0.1.1.data/data/share/jupyter/labextensions/ploomber-extension/static/204.89d5b0c27f8042a09438.js
ploomber_extension-0.1.1.data/data/share/jupyter/labextensions/ploomber-extension/static/28.1f003d1611e9a92b831a.js
ploomber_extension-0.1.1.data/data/share/jupyter/labextensions/ploomber-extension/static/28.1f003d1611e9a92b831a.js.LICENSE.txt
ploomber_extension-0.1.1.data/data/share/jupyter/labextensions/ploomber-extension/static/336.a809a73426cd24d77c68.js
ploomber_extension-0.1.1.data/data/share/jupyter/labextensions/ploomber-extension/static/336.a809a73426cd24d77c68.js.LICENSE.txt
ploomber_extension-0.1.1.data/data/share/jupyter/labextensions/ploomber-extension/static/408.f1c11b0d4cc82551e2d1.js
ploomber_extension-0.1.1.data/data/share/jupyter/labextensions/ploomber-extension/static/448.f34edb745ede6ce75828.js
ploomber_extension-0.1.1.data/data/share/jupyter/labextensions/ploomber-extension/static/448.f34edb745ede6ce75828.js.LICENSE.txt
ploomber_extension-0.1.1.data/data/share/jupyter/labextensions/ploomber-extension/static/736.51427e9d0a00dd2006b4.js
ploomber_extension-0.1.1.dist-info/METADATA
ploomber_extension-0.1.1.dist-info/WHEEL
ploomber_extension-0.1.1.dist-info/licenses/LICENSE
ploomber_extension-0.1.1.dist-info/RECORD
